LICENSE
LICENSE.txt
README.rst
setup.cfg
setup.py
heryisengineer/__init__.py
heryisengineer/engineer.py
heryisengineer.egg-info/PKG-INFO
heryisengineer.egg-info/SOURCES.txt
heryisengineer.egg-info/dependency_links.txt
heryisengineer.egg-info/top_level.txt